envoy/__init__.py
envoy/_bin/__init__.py
envoy/_bin/envoy
envoy/_envoy.py
envoy/_main.py
envoy_server-1.37.0.dist-info/licenses/LICENSE
envoy_server-1.37.0.dist-info/WHEEL
envoy_server-1.37.0.dist-info/entry_points.txt
envoy_server-1.37.0.dist-info/METADATA
envoy_server-1.37.0.dist-info/RECORD
