Metadata-Version: 2.4
Name: envoy-server
Version: 1.37.0
Summary: A Python wheel distribution of the Envoy server
Keywords: envoy
Author: CurioSwitch
License-File: LICENSE
Classifier: Development Status :: 5 - Production/Stable
Classifier: Environment :: Console
Classifier: Intended Audience :: Developers
Classifier: License :: OSI Approved :: MIT License
Classifier: Operating System :: MacOS :: MacOS X
Classifier: Operating System :: Microsoft :: Windows
Classifier: Operating System :: POSIX :: Linux
Classifier: Programming Language :: Python :: 3
Classifier: Programming Language :: Python :: 3 :: Only
Classifier: Programming Language :: Python :: 3.10
Classifier: Programming Language :: Python :: 3.11
Classifier: Programming Language :: Python :: 3.12
Classifier: Programming Language :: Python :: 3.13
Classifier: Programming Language :: Python :: 3.14
Classifier: Topic :: Internet :: Proxy Servers
Classifier: Topic :: Internet :: WWW/HTTP :: HTTP Servers
Classifier: Topic :: System :: Networking
Requires-Python: >=3.10
Project-URL: Changelog, https://github.com/curioswitch/py-envoy-server/releases
Project-URL: Homepage, https://github.com/curioswitch/py-envoy-server
Project-URL: Issues, https://github.com/curioswitch/py-envoy-server/issues
Project-URL: Repository, https://github.com/curioswitch/py-envoy-server.git
